onepm_shims-24.1.1.dist-info/METADATA
onepm_shims-24.1.1.dist-info/WHEEL
onepm_shims-24.1.1.dist-info/entry_points.txt
onepm_shims-24.1.1.dist-info/licenses/LICENSE
onepm_shims/__init__.py
onepm_shims/shims.py
onepm_shims-24.1.1.dist-info/RECORD
